{
  "_id": "page.start",
  "_type": "page.start",
  "body": "",
  "heading": "Confiscation Order",
  "lede": "",
  "steps": [
    "page.county-court",
    "page.location-code",
    "page.case-number",
    "page.reference-number",
    "page.section",
    "page.date",
    "page.variation-made",
    "page.original-order-date",
    "page.accrued-interest-varied",
    "page.priority-order-varied",
    "page.defendant-name",
    "page.defendant-date-of-birth",
    "page.defendant-nationality",
    "page.defendant-address",
    "page.custody-location",
    "page.conviction-date",
    "page.offence",
    "page.magistrates-court",
    "page.amount",
    "page.recovered-amount",
    "page.payment-dates",
    "page.joint-benefit-case",
    "page.benefit-details"
  ],
  "url": "/"
}